<annotation>
	<folder>train_image_folder</folder>
	<filename>00940.jpg</filename>
	<path>D:\Projects\Internal\wear-helmet-detection\keras-yolo2\train_image_folder\00940.jpg</path>
	<source>
		<database>Unknown</database>
	</source>
	<size>
		<width>275</width>
		<height>183</height>
		<depth>3</depth>
	</size>
	<segmented>0</segmented>
	<object>
		<name>helmet</name>
		<pose>Unspecified</pose>
		<truncated>0</truncated>
		<difficult>0</difficult>
		<bndbox>
			<xmin>139</xmin>
			<ymin>14</ymin>
			<xmax>218</xmax>
			<ymax>69</ymax>
		</bndbox>
	</object>
	<object>
		<name>helmet</name>
		<pose>Unspecified</pose>
		<truncated>0</truncated>
		<difficult>0</difficult>
		<bndbox>
			<xmin>83</xmin>
			<ymin>63</ymin>
			<xmax>142</xmax>
			<ymax>106</ymax>
		</bndbox>
	</object>
	<object>
		<name>helmet</name>
		<pose>Unspecified</pose>
		<truncated>0</truncated>
		<difficult>0</difficult>
		<bndbox>
			<xmin>25</xmin>
			<ymin>33</ymin>
			<xmax>72</xmax>
			<ymax>76</ymax>
		</bndbox>
	</object>
	<object>
		<name>person with full safety</name>
		<pose>Unspecified</pose>
		<truncated>1</truncated>
		<difficult>0</difficult>
		<bndbox>
			<xmin>17</xmin>
			<ymin>34</ymin>
			<xmax>80</xmax>
			<ymax>183</ymax>
		</bndbox>
	</object>
	<object>
		<name>person with full safety</name>
		<pose>Unspecified</pose>
		<truncated>0</truncated>
		<difficult>0</difficult>
		<bndbox>
			<xmin>81</xmin>
			<ymin>62</ymin>
			<xmax>165</xmax>
			<ymax>177</ymax>
		</bndbox>
	</object>
	<object>
		<name>person with full safety</name>
		<pose>Unspecified</pose>
		<truncated>1</truncated>
		<difficult>0</difficult>
		<bndbox>
			<xmin>139</xmin>
			<ymin>12</ymin>
			<xmax>244</xmax>
			<ymax>183</ymax>
		</bndbox>
	</object>
	<object>
		<name>safety vest</name>
		<pose>Unspecified</pose>
		<truncated>0</truncated>
		<difficult>0</difficult>
		<bndbox>
			<xmin>16</xmin>
			<ymin>88</ymin>
			<xmax>78</xmax>
			<ymax>179</ymax>
		</bndbox>
	</object>
	<object>
		<name>safety vest</name>
		<pose>Unspecified</pose>
		<truncated>0</truncated>
		<difficult>0</difficult>
		<bndbox>
			<xmin>103</xmin>
			<ymin>124</ymin>
			<xmax>156</xmax>
			<ymax>181</ymax>
		</bndbox>
	</object>
	<object>
		<name>safety vest</name>
		<pose>Unspecified</pose>
		<truncated>1</truncated>
		<difficult>0</difficult>
		<bndbox>
			<xmin>148</xmin>
			<ymin>117</ymin>
			<xmax>238</xmax>
			<ymax>183</ymax>
		</bndbox>
	</object>
</annotation>